[
    {
        "nome": "gabriel",
        "compras": [
            {
                "alimentacao": [
                    1222.0
                ],
                "higiene": [
                    30.0
                ],
                "transporte": [
                    123.0
                ],
                "roupa": [
                    40.0,
                    2.0,
                    12.0
                ],
                "lazer": [
                    90.0
                ]
            }
        ]
    },
    {
        "nome": "lucas",
        "compras": [
            {
                "alimentacao": [],
                "higiene": [],
                "transporte": [],
                "roupa": [
                    20.0
                ],
                "lazer": []
            }
        ]
    }
]